fastapi_geolocation/__init__.py
fastapi_geolocation/geoip.py
fastapi_geolocation/middleware.py
fastapi_geolocation/resources.py
fastapi_geolocation/service.py
fastapi_geolocation-1.0.1.dist-info/LICENSE
fastapi_geolocation-1.0.1.dist-info/METADATA
fastapi_geolocation-1.0.1.dist-info/WHEEL
fastapi_geolocation-1.0.1.dist-info/top_level.txt
fastapi_geolocation-1.0.1.dist-info/RECORD
