Metadata-Version: 2.1
Name: fastapi-geolocation
Version: 1.0.1
Summary: FastAPI Geolocation
Author-email: Nurettin Abacı <abacinurettin@gmail.com>
License: The MIT License (MIT)
Project-URL: Homepage, https://github.com/nurettn/fastapi-geolocation
Project-URL: Repository, https://github.com/nurettn/fastapi-geolocation
Keywords: fastapi,geolocation
Classifier: License :: OSI Approved :: MIT License
Classifier: Programming Language :: Python
Classifier: Programming Language :: Python :: 3
Classifier: Operating System :: OS Independent
Classifier: Topic :: Internet
Classifier: Topic :: Software Development :: Libraries :: Python Modules
Classifier: Typing :: Typed
Requires-Python: >=3.8
License-File: LICENSE
Requires-Dist: fastapi >=0.92.0
Provides-Extra: dev
Requires-Dist: black ; extra == 'dev'
Requires-Dist: bumpver ; extra == 'dev'
Requires-Dist: isort ; extra == 'dev'
Requires-Dist: mypy ; extra == 'dev'
